PyStatsLearn/PyLearn.py
PyStatsLearn/__init__.py
PyStatsLearn-0.0.1.dist-info/LICENSE.txt
PyStatsLearn-0.0.1.dist-info/METADATA
PyStatsLearn-0.0.1.dist-info/WHEEL
PyStatsLearn-0.0.1.dist-info/top_level.txt
PyStatsLearn-0.0.1.dist-info/RECORD
