Metadata-Version: 2.1
Name: PyStatsLearn
Version: 0.0.1
Summary: This is a python module which is made for learning purpose.
Home-page: https://github.com/Hiten-98/PyStatsLearn/tree/main
Author: Hiten Mandaliya
Author-email: hitenmandaliya562@gmail.com
License: UNKNOWN
Platform: UNKNOWN
Classifier: Programming Language :: Python :: 3
Classifier: License :: OSI Approved :: MIT License
Classifier: Operating System :: OS Independent
Requires-Python: >=3.6
License-File: LICENSE.txt
